[
    {
      "category": "Bodybuilding",
      "description": "Build strength and muscle mass through resistance training.",
      "img": "https://i.ibb.co/9H6ZXP2/pexels-pixabay-50597.jpg"
    },
    {
      "category": "Yoga",
      "description": "Improve flexibility, balance, and mental well-being through various yoga poses.",
      "img": "https://i.ibb.co/9Y5t2nP/pexels-cottonbro-studio-4325484.jpg"
    },
    {
      "category": "Cardio",
      "description": "Enhance cardiovascular health with aerobic exercises like running and cycling.",
      "img": "https://i.ibb.co/kqGWSNw/pexels-william-choquette-1954524.jpg"
    },
    {
      "category": "Crossfit",
      "description": "Combine various functional movements at high intensity for a full-body workout.",
      "img": "https://i.ibb.co/p3ThM1G/pexels-jonathan-borba-3076511.jpg"
    },
   
    {
      "category": "Weightlifting",
      "description": "Focus on lifting weights to build muscle strength and power.",
      "img": "https://i.ibb.co/2FcMHvf/pexels-victor-freitas-2261477.jpg"
    },
   
   
    {
      "category": "Functional Training",
      "description": "Engage in exercises that mimic everyday movements to enhance overall fitness.",
      "img": "https://i.ibb.co/nLYB5Lq/pexels-julia-larson-6455791.jpg"
    },
    {
      "category": "Kickboxing",
      "description": "Combine martial arts techniques with cardio for a high-energy workout.",
      "img": "https://i.ibb.co/2j0BsFP/pexels-rdne-stock-project-8612580.jpg"
    }
  ]
  